{
  "obsidian-git:commit-specified-message": [
    {
      "modifiers": [
        "Alt",
        "Shift"
      ],
      "key": "C"
    }
  ],
  "obsidian-git:init-repo": [
    {
      "modifiers": [
        "Alt",
        "Shift"
      ],
      "key": "I"
    }
  ],
  "obsidian-git:pull": [
    {
      "modifiers": [
        "Alt",
        "Shift"
      ],
      "key": "D"
    }
  ],
  "obsidian-git:push2": [
    {
      "modifiers": [
        "Alt",
        "Shift"
      ],
      "key": "U"
    }
  ]
}